networktest/__init__.py
networktest/blocker.py
networktest/testcase.py
networktest/mock/__init__.py
networktest/mock/api.py
networktest/mock/http.py
networktest/pytest/__init__.py
networktest/pytest/integration.py
networktest/pytest/plugin.py
networktest-2.0.1.dist-info/LICENSE
networktest-2.0.1.dist-info/METADATA
networktest-2.0.1.dist-info/WHEEL
networktest-2.0.1.dist-info/entry_points.txt
networktest-2.0.1.dist-info/top_level.txt
networktest-2.0.1.dist-info/RECORD
